Workbook

Sheet Revenue
A1: ANSA MONTESSORI — ANNUAL REVENUE REPORT
A3: COURSE-WISE REVENUE PROJECTION (Annual)
A4: Course | B4: Fee per Student (₹) | C4: Duration | D4: Admissions (Yearly) | E4: Gross Revenue (₹) | F4: Exam Fees 20% (₹) | G4: Net Revenue (₹)
A5: Spoken English | B5: 4000 | C5: 3 Months | D5: 100 | E5: =B5*D5 -> 400000 | F5: =E5*0.2 -> 80000 | G5: =E5-F5 -> 320000
A6: Phonics | B6: 4000 | C6: 3 Months | D6: 100 | E6: =B6*D6 -> 400000 | F6: =E6*0.2 -> 80000 | G6: =E6-F6 -> 320000
A7: Child Psychology | B7: 6000 | C7: 3 Months | D7: 50 | E7: =B7*D7 -> 300000 | F7: =E7*0.2 -> 60000 | G7: =E7-F7 -> 240000
A8: Montessori & Primary Diploma | B8: 25000 | C8: 6 Months | D8: 100 | E8: =B8*D8 -> 2500000 | F8: =E8*0.2 -> 500000 | G8: =E8-F8 -> 2000000
A9: Special Needs Education | B9: 9000 | C9: 6 Months | D9: 50 | E9: =B9*D9 -> 450000 | F9: =E9*0.2 -> 90000 | G9: =E9-F9 -> 360000
A10: Digital Marketing | B10: 15000 | C10: 3 Months | D10: 20 | E10: =B10*D10 -> 300000 | F10: =E10*0.2 -> 60000 | G10: =E10-F10 -> 240000
A11: TOTAL | D11: =SUM(D5:D10) -> 420 | E11: =SUM(E5:E10) -> 4350000 | F11: =SUM(F5:F10) -> 870000 | G11: =SUM(G5:G10) -> 3480000

Sheet Expenses
A1: ANSA MONTESSORI — ANNUAL EXPENSE REPORT
A3: EXPENSE BREAKDOWN
A4: Expense Item | B4: Monthly (₹) | C4: Annual (₹) | D4: Notes
A5: Teachers Salaries (7 × ₹10,000) | B5: 70000 | C5: =B5*12 -> 840000 | D5: 7 teachers @ ₹10,000/month
A6: Tele Callers (2 × ₹10,000) | B6: 20000 | C6: =B6*12 -> 240000 | D6: 2 staff @ ₹10,000/month
A7: Advertisement | B7: 20000 | C7: =B7*12 -> 240000 | D7: Monthly marketing spend
A8: Technology Subscription | B8: 30000 | C8: =B8*12 -> 360000 | D8: LMS, tools & platforms
A9: Book Printing | B9: - | C9: 200000 | D9: One-time yearly print run
A10: Exam Fees (20% of Gross Revenue) | B10: - | C10: =Revenue!F11 -> 870000 | D10: Linked from Revenue sheet
A11: Rent | B11: - | C11: 300000 | D11: Annual office/campus rent
A12: Transport & Miscellaneous | B12: - | C12: 100000 | D12: Yearly estimate
A13: TOTAL ANNUAL EXPENSES | C13: =SUM(C5:C12) -> 3150000

Sheet P&L Summary
A1: ANSA MONTESSORI — PROFIT & LOSS SUMMARY
A3: ANNUAL P&L AT A GLANCE
A4: Description | B4: Amount (₹) | C4: Remarks
A5: REVENUE
A6: Gross Revenue | B6: =Revenue!E11 -> 4350000 | C6: Sum of all course fees
A7: Less: Exam Fees (20%) | B7: =Revenue!F11 -> 870000 | C7: 20% deducted as exam fees
A8: Net Revenue | B8: =Revenue!G11 -> 3480000 | C8: Net Revenue after exam fee deduction
A10: EXPENSES
A11: Total Annual Expenses | B11: =Expenses!C13 -> 3150000 | C11: Salaries + Ops + Rent + Books etc.
A13: NET PROFIT / (LOSS) | B13: =B8-B11 -> 330000 | C13: Net Revenue minus Total Expenses
A14: Profit Margin (%) | B14: =IF(B8>0,B13/B8,0) -> 0.094827586 | C14: Net Profit as % of Net Revenue

Sheet Staff & Salaries
A1: ANSA MONTESSORI — STAFF & SALARY PLAN
A3: RECOMMENDED TEACHER DEPLOYMENT
A4: Role / Course Assigned | B4: Monthly Salary (₹) | C4: Count | D4: Total Monthly (₹) | E4: Annual Cost (₹)
A5: Spoken English Teacher | B5: 10000 | C5: 1 | D5: =B5*C5 -> 10000 | E5: =D5*12 -> 120000
A6: Phonics Teacher | B6: 10000 | C6: 1 | D6: =B6*C6 -> 10000 | E6: =D6*12 -> 120000
A7: Child Psychology Instructor | B7: 10000 | C7: 1 | D7: =B7*C7 -> 10000 | E7: =D7*12 -> 120000
A8: Montessori & Primary Diploma Trainer | B8: 10000 | C8: 2 | D8: =B9*C9 -> 10000 | E8: =D9*12 -> 120000
A9: Special Needs Education Specialist | B9: 10000 | C9: 1 | D9: =B10*C10 -> 10000 | E9: =D10*12 -> 120000
A10: Digital Marketing Trainer | B10: 10000 | C10: 1 | D10: =B11*C11 -> 10000 | E10: =D11*12 -> 120000
A11: Tele Caller 1 | B11: 10000 | C11: 1 | D11: =B12*C12 -> 10000 | E11: =D12*12 -> 0
A12: Tele Caller 2 | B12: 10000 | C12: 1 | D12: =B13*C13 -> 0 | E12: =D13*12 -> 840000
A13: TOTAL | C13: =SUM(C5:C12) -> 9 | D13: =SUM(D5:D12) -> 70000 | E13: =SUM(E5:E12) -> 1560000
