Workbook

Sheet Dashboard
A1: ANSA MONTESSORI TEACHER TRAINING INSTITUTE — FINANCIAL DASHBOARD
A2: Powered by Inspireway Education Services Pvt Ltd | Annual Financial Report
B5: GROSS REVENUE | D5: NET REVENUE | F5: TOTAL EXPENSES | H5: NET PROFIT | J5: PROFIT MARGIN
B6: =Revenue!E11 -> 4350000 | D6: ='P&L Summary'!B8 -> 4132500 | F6: =Expenses!C18 -> 2257500 | H6: ='P&L Summary'!B10 -> 2092500 | J6: ='P&L Summary'!B11 -> 0.48103448
A10: COURSE-WISE REVENUE SUMMARY
B11: Course | C11: Fee (₹) | D11: Admissions | E11: Gross Rev (₹) | F11: Exam Fee (₹) | G11: Net Rev (₹) | H11: % of Total
B12: Spoken English | C12: =Revenue!B5 -> 4000 | D12: =Revenue!D5 -> 100 | E12: =Revenue!E5 -> 400000 | F12: =Revenue!F5 -> 20000 | G12: =Revenue!G5 -> 380000 | H12: =IF(Revenue!E11>0,Revenue!G5/Revenue!E11,0) -> 0.087356322
B13: Phonics & Early Literacy | C13: =Revenue!B6 -> 4000 | D13: =Revenue!D6 -> 100 | E13: =Revenue!E6 -> 400000 | F13: =Revenue!F6 -> 20000 | G13: =Revenue!G6 -> 380000 | H13: =IF(Revenue!E11>0,Revenue!G6/Revenue!E11,0) -> 0.087356322
B14: Child Psychology | C14: =Revenue!B7 -> 6000 | D14: =Revenue!D7 -> 50 | E14: =Revenue!E7 -> 300000 | F14: =Revenue!F7 -> 15000 | G14: =Revenue!G7 -> 285000 | H14: =IF(Revenue!E11>0,Revenue!G7/Revenue!E11,0) -> 0.065517241
B15: Montessori & Primary Diploma | C15: =Revenue!B8 -> 25000 | D15: =Revenue!D8 -> 100 | E15: =Revenue!E8 -> 2500000 | F15: =Revenue!F8 -> 125000 | G15: =Revenue!G8 -> 2375000 | H15: =IF(Revenue!E11>0,Revenue!G8/Revenue!E11,0) -> 0.54597701
B16: Special Needs Education | C16: =Revenue!B9 -> 9000 | D16: =Revenue!D9 -> 50 | E16: =Revenue!E9 -> 450000 | F16: =Revenue!F9 -> 22500 | G16: =Revenue!G9 -> 427500 | H16: =IF(Revenue!E11>0,Revenue!G9/Revenue!E11,0) -> 0.098275862
B17: Digital Marketing | C17: =Revenue!B10 -> 15000 | D17: =Revenue!D10 -> 20 | E17: =Revenue!E10 -> 300000 | F17: =Revenue!F10 -> 15000 | G17: =Revenue!G10 -> 285000 | H17: =IF(Revenue!E11>0,Revenue!G10/Revenue!E11,0) -> 0.065517241
B18: TOTAL | D18: =Revenue!D11 -> 420 | E18: =Revenue!E11 -> 4350000 | F18: =Revenue!F11 -> 217500 | G18: =Revenue!G11 -> 4132500 | H18: =100% -> 1
A22: EXPENSE SUMMARY
B23: Expense Item | D23: Annual Amount (₹) | F23: % of Total Expenses
B24: Teacher & Staff Salaries | D24: =Expenses!C5+Expenses!C6 -> 840000 | F24: =IF(Expenses!C12>0,(Expenses!C5+Expenses!C6)/Expenses!C12,0) -> 0.41176471
B25: Advertisement | D25: =Expenses!C7 -> 240000 | F25: =IF(Expenses!C12>0,Expenses!C7/Expenses!C12,0) -> 0.11764706
B26: Technology Subscription | D26: =Expenses!C8 -> 360000 | F26: =IF(Expenses!C12>0,Expenses!C8/Expenses!C12,0) -> 0.17647059
B27: Book Printing | D27: =Expenses!C9 -> 200000 | F27: =IF(Expenses!C12>0,Expenses!C9/Expenses!C12,0) -> 0.098039216
B28: Exam Fees (20% Gross) | D28: =Expenses!C10 -> 300000 | F28: =IF(Expenses!C12>0,Expenses!C10/Expenses!C12,0) -> 0.14705882
B29: Rent | D29: =Expenses!C11 -> 100000 | F29: =IF(Expenses!C12>0,Expenses!C11/Expenses!C12,0) -> 0.049019608
B30: Transport & Misc | D30: =Expenses!C12 -> 2040000 | F30: =IF(Expenses!C12>0,Expenses!C12/Expenses!C12,0) -> 1
B31: TOTAL EXPENSES | D31: =Expenses!C12 -> 2040000 | F31: =100% -> 1
A33: ENROLLMENT FUNNEL SNAPSHOT
B34: Stage | D34: Count | F34: Conv. Rate | H34: Status
B35: Leads Received | D35: ='Enrollment Funnel'!B6 -> 1000 | F35: — | H35: ='Enrollment Funnel'!G6 -> ✅ On Track
B36: Enquiry Calls Made | D36: ='Enrollment Funnel'!B7 -> 700 | F36: ='Enrollment Funnel'!C7 -> 0.7 | H36: ='Enrollment Funnel'!G7 -> ✅ On Track
B37: Counselling Completed | D37: ='Enrollment Funnel'!B8 -> 400 | F37: ='Enrollment Funnel'!C8 -> 0.4 | H37: ='Enrollment Funnel'!G8 -> ⚠️ Below Target
B38: Applications Submitted | D38: ='Enrollment Funnel'!B9 -> 200 | F38: ='Enrollment Funnel'!C9 -> 0.2 | H38: ='Enrollment Funnel'!G9 -> ⚠️ Below Target
B39: Confirmed Admissions | D39: ='Enrollment Funnel'!B10 -> 0 | F39: ='Enrollment Funnel'!C10 -> 0 | H39: ='Enrollment Funnel'!G10 -> ⚠️ Below Target
B40: Course Completions | D40: ='Enrollment Funnel'!B12 -> 350 | F40: ='Enrollment Funnel'!C12 -> 0.35 | H40: ='Enrollment Funnel'!G11 -> ✅ On Track
B41: Placed / Employed | D41: ='Enrollment Funnel'!B13 -> 343 | F41: ='Enrollment Funnel'!C13 -> 0.343 | H41: ='Enrollment Funnel'!G12 -> ⚠️ Below Target

Sheet Revenue
A1: ANSA MONTESSORI — ANNUAL REVENUE REPORT
A3: COURSE-WISE REVENUE PROJECTION (Annual)
A4: Course | B4: Fee per Student (₹) | C4: Duration | D4: Admissions (Yearly) | E4: Gross Revenue (₹) | F4: Exam Fees 5% (₹) | G4: Net Revenue (₹)
A5: Spoken English | B5: 4000 | C5: 3 Months | D5: 100 | E5: =B5*D5 -> 400000 | F5: =E5*0.05 -> 20000 | G5: =E5-F5 -> 380000
A6: Phonics | B6: 4000 | C6: 3 Months | D6: 100 | E6: =B6*D6 -> 400000 | F6: =E6*0.05 -> 20000 | G6: =E6-F6 -> 380000
A7: Child Psychology | B7: 6000 | C7: 3 Months | D7: 50 | E7: =B7*D7 -> 300000 | F7: =E7*0.05 -> 15000 | G7: =E7-F7 -> 285000
A8: Montessori & Primary Diploma | B8: 25000 | C8: 6 Months | D8: 100 | E8: =B8*D8 -> 2500000 | F8: =E8*0.05 -> 125000 | G8: =E8-F8 -> 2375000
A9: Special Needs Education | B9: 9000 | C9: 6 Months | D9: 50 | E9: =B9*D9 -> 450000 | F9: =E9*0.05 -> 22500 | G9: =E9-F9 -> 427500
A10: Digital Marketing | B10: 15000 | C10: 3 Months | D10: 20 | E10: =B10*D10 -> 300000 | F10: =E10*0.05 -> 15000 | G10: =E10-F10 -> 285000
A11: TOTAL | D11: =SUM(D5:D10) -> 420 | E11: =SUM(E5:E10) -> 4350000 | F11: =SUM(F5:F10) -> 217500 | G11: =SUM(G5:G10) -> 4132500

Sheet Expenses
A1: ANSA MONTESSORI — ANNUAL EXPENSE SUMMARY
A2: 📌 Staff reduced to 5 teachers + 2 tele callers (₹8.4L/yr) | Exam Fees = 5% of Gross (₹2.175L) | All other ops unchanged
A3: OPERATIONAL EXPENSES
A4: Expense Category | B4: Monthly (₹) | C4: Annual (₹) | D4: % of Gross Revenue
A5: Staff Salaries — 5 Teachers (₹10K/mo each) | B5: 50000 | C5: 600000 | D5: =C5/Revenue!E11 -> 0.13793103
A6: Tele Callers — 2 Staff (₹10K/mo each) | B6: 20000 | C6: 240000 | D6: =C6/Revenue!E11 -> 0.055172414
A7: Advertisement | B7: 20000 | C7: 240000 | D7: =C7/Revenue!E11 -> 0.055172414
A8: Technology / LMS | B8: 30000 | C8: 360000 | D8: =C8/Revenue!E11 -> 0.082758621
A9: Book Printing | B9: — | C9: 200000 | D9: =C9/Revenue!E11 -> 0.045977011
A10: Rent | B10: 25000 | C10: 300000 | D10: =C10/Revenue!E11 -> 0.068965517
A11: Misc / Other | B11: — | C11: 100000 | D11: =C11/Revenue!E11 -> 0.022988506
A12: TOTAL OPERATIONAL EXPENSES | B12: =SUM(B5:B11) -> 145000 | C12: =SUM(C5:C11) -> 2040000 | D12: =C12/Revenue!E11 -> 0.46896552
A14: FIXED DEDUCTION (5% of Gross Revenue)
A15: Expense Category | B15: Rate | C15: Annual (₹) | D15: % of Gross Revenue
A16: Exam Fees (5% of Gross Revenue) | B16: 5.0% | C16: =Revenue!E11*0.05 -> 217500 | D16: =C16/Revenue!E11 -> 0.05
A18: GRAND TOTAL EXPENSES (Ops + Exam Fees) | B18: — | C18: =C12+C16 -> 2257500 | D18: =C18/Revenue!E11 -> 0.51896552
A20: ✅ Net Revenue = ₹41.325L | Net Profit = ₹21.325L | Profit Margin = 49.0% | Total Savings vs original = ₹14.925L/yr

Sheet P&L Summary
A1: ANSA MONTESSORI — PROFIT & LOSS SUMMARY
A3: FY 2026–27 | 5 Teachers | Exam Fees 5% | Net Profit ₹21.33L
A4: Line Item | B4: Amount (₹) | C4: % of Gross Revenue
A6: GROSS REVENUE | B6: =Revenue!E11 -> 4350000 | C6: =IF(Revenue!E11>0,B6/Revenue!E11,0) -> 1
A7: Less: Exam Fees (5% of Gross) | B7: =Revenue!E11*0.05 -> 217500 | C7: =IF(Revenue!E11>0,B7/Revenue!E11,0) -> 0.05
A8: NET REVENUE | B8: =B6-B7 -> 4132500 | C8: =IF(Revenue!E11>0,B8/Revenue!E11,0) -> 0.95
A9: Less: Operational Expenses | B9: =Expenses!C12 -> 2040000 | C9: =IF(Revenue!E11>0,B9/Revenue!E11,0) -> 0.46896552
A10: NET PROFIT | B10: =B8-B9 -> 2092500 | C10: =IF(Revenue!E11>0,B10/Revenue!E11,0) -> 0.48103448
A11: Profit Margin (% of Gross) | B11: =IF(B6>0,B10/B6,0) -> 0.48103448 | C11: =B11 -> 0.48103448
A12: Return on Net Revenue | B12: =IF(B8>0,B10/B8,0) -> 0.50635209 | C12: =B12 -> 0.50635209
A13: Total Expense Ratio | B13: =IF(B6>0,Expenses!C18/B6,0) -> 0.51896552 | C13: =B13 -> 0.51896552

Sheet Staff & Salaries
A1: ANSA MONTESSORI — STAFF & SALARY PLAN (5 TEACHERS + 2 TELE CALLERS)
A2: 📌 Reduced from 10 to 5 core teachers | Exam Fees reduced to 5% of Gross | Total salary cost: ₹8.4L/yr
A3: TEACHING & SUPPORT STAFF
A4: Role / Course Assigned | B4: Monthly Salary (₹) | C4: Count | D4: Total Monthly (₹) | E4: Annual Cost (₹)
A5: Montessori & Primary Diploma Trainer | B5: 10000 | C5: 1 | D5: =B5*C5 -> 10000 | E5: =D5*12 -> 120000
A6: Special Needs Education Specialist | B6: 10000 | C6: 1 | D6: =B6*C6 -> 10000 | E6: =D6*12 -> 120000
A7: Spoken English Teacher | B7: 10000 | C7: 1 | D7: =B7*C7 -> 10000 | E7: =D7*12 -> 120000
A8: Phonics & Early Literacy Teacher | B8: 10000 | C8: 1 | D8: =B8*C8 -> 10000 | E8: =D8*12 -> 120000
A9: Child Psychology Instructor | B9: 10000 | C9: 1 | D9: =B9*C9 -> 10000 | E9: =D9*12 -> 120000
A10: Tele Caller 1 | B10: 10000 | C10: 1 | D10: =B10*C10 -> 10000 | E10: =D10*12 -> 120000
A11: Tele Caller 2 | B11: 10000 | C11: 1 | D11: =B11*C11 -> 10000 | E11: =D11*12 -> 120000
A12: TOTAL (5 Teachers + 2 Tele Callers) | C12: =SUM(C5:C11) -> 7 | D12: =SUM(D5:D11) -> 70000 | E12: =SUM(E5:E11) -> 840000
A14: ❌ REMOVED: Spoken English Teacher #2 | Montessori Trainer #2 (Junior) | Digital Marketing Trainer | Child Psych Asst. | Special Needs Asst.

Sheet Course Profitability
A1: ANSA MONTESSORI — COURSE-WISE PROFITABILITY ANALYSIS
A3: REVENUE, COST & MARGIN PER COURSE
A4: Course | B4: Admissions | C4: Fee (₹) | D4: Gross Rev (₹) | E4: Est. Cost/Student (₹) | F4: Total Cost (₹) | G4: Contribution (₹) | H4: Margin %
A5: Spoken English | B5: =Revenue!D5 -> 100 | C5: =Revenue!B5 -> 4000 | D5: =Revenue!E5 -> 400000 | E5: 1500 | F5: =E5*B5 -> 150000 | G5: =D5-F5 -> 250000 | H5: =IF(D5>0,G5/D5,0) -> 0.625
A6: Phonics & Early Literacy | B6: =Revenue!D6 -> 100 | C6: =Revenue!B6 -> 4000 | D6: =Revenue!E6 -> 400000 | E6: 1500 | F6: =E6*B6 -> 150000 | G6: =D6-F6 -> 250000 | H6: =IF(D6>0,G6/D6,0) -> 0.625
A7: Child Psychology | B7: =Revenue!D7 -> 50 | C7: =Revenue!B7 -> 6000 | D7: =Revenue!E7 -> 300000 | E7: 2000 | F7: =E7*B7 -> 100000 | G7: =D7-F7 -> 200000 | H7: =IF(D7>0,G7/D7,0) -> 0.66666667
A8: Montessori & Primary Diploma | B8: =Revenue!D8 -> 100 | C8: =Revenue!B8 -> 25000 | D8: =Revenue!E8 -> 2500000 | E8: 5000 | F8: =E8*B8 -> 500000 | G8: =D8-F8 -> 2000000 | H8: =IF(D8>0,G8/D8,0) -> 0.8
A9: Special Needs Education | B9: =Revenue!D9 -> 50 | C9: =Revenue!B9 -> 9000 | D9: =Revenue!E9 -> 450000 | E9: 2500 | F9: =E9*B9 -> 125000 | G9: =D9-F9 -> 325000 | H9: =IF(D9>0,G9/D9,0) -> 0.72222222
A10: Digital Marketing | B10: =Revenue!D10 -> 20 | C10: =Revenue!B10 -> 15000 | D10: =Revenue!E10 -> 300000 | E10: 3000 | F10: =E10*B10 -> 60000 | G10: =D10-F10 -> 240000 | H10: =IF(D10>0,G10/D10,0) -> 0.8
A11: TOTAL | B11: =SUM(B5:B10) -> 420 | D11: =SUM(D5:D10) -> 4350000 | F11: =SUM(F5:F10) -> 1085000 | G11: =SUM(G5:G10) -> 3265000 | H11: =IF(D11>0,G11/D11,0) -> 0.75057471
A13: 📌 Est. Cost/Student (col E) = allocated teacher & ops cost. Adjust blue cells as needed.

Sheet Monthly Cash Flow
A1: ANSA MONTESSORI — MONTHLY CASH FLOW | April 2026 – March 2027
A2: Revenue recognised by course duration & batch schedule • Expenses spread monthly • Book Printing charged in April
A3: COURSE-WISE MONTHLY REVENUE RECOGNITION
A4: Course | B4: Apr-26 | C4: May-26 | D4: Jun-26 | E4: Jul-26 | F4: Aug-26 | G4: Sep-26 | H4: Oct-26 | I4: Nov-26 | J4: Dec-26 | K4: Jan-27 | L4: Feb-27 | M4: Mar-27 | N4: ANNUAL TOTAL | O4: Revenue Sheet
A5: Spoken English | B5: 33333 | C5: 33333 | D5: 33333 | E5: 33333 | F5: 33333 | G5: 33333 | H5: 33333 | I5: 33333 | J5: 33333 | K5: 33333 | L5: 33333 | M5: 33333 | N5: =SUM(B5:M5) -> 399996 | O5: =Revenue!E5 -> 400000
A6: Phonics & Early Literacy | B6: 33333 | C6: 33333 | D6: 33333 | E6: 33333 | F6: 33333 | G6: 33333 | H6: 33333 | I6: 33333 | J6: 33333 | K6: 33333 | L6: 33333 | M6: 33333 | N6: =SUM(B6:M6) -> 399996 | O6: =Revenue!E6 -> 400000
A7: Child Psychology | B7: 25000 | C7: 25000 | D7: 25000 | E7: 25000 | F7: 25000 | G7: 25000 | H7: 25000 | I7: 25000 | J7: 25000 | K7: 25000 | L7: 25000 | M7: 25000 | N7: =SUM(B7:M7) -> 300000 | O7: =Revenue!E7 -> 300000
A8: Montessori & Primary Diploma | B8: 208333 | C8: 208333 | D8: 208333 | E8: 208333 | F8: 208333 | G8: 208333 | H8: 208333 | I8: 208333 | J8: 208333 | K8: 208333 | L8: 208333 | M8: 208333 | N8: =SUM(B8:M8) -> 2499996 | O8: =Revenue!E8 -> 2500000
A9: Special Needs Education | B9: 37500 | C9: 37500 | D9: 37500 | E9: 37500 | F9: 37500 | G9: 37500 | H9: 37500 | I9: 37500 | J9: 37500 | K9: 37500 | L9: 37500 | M9: 37500 | N9: =SUM(B9:M9) -> 450000 | O9: =Revenue!E9 -> 450000
A10: Digital Marketing | B10: 25000 | C10: 25000 | D10: 25000 | E10: 25000 | F10: 25000 | G10: 25000 | H10: 25000 | I10: 25000 | J10: 25000 | K10: 25000 | L10: 25000 | M10: 25000 | N10: =SUM(B10:M10) -> 300000 | O10: =Revenue!E10 -> 300000
A11: GROSS REVENUE | B11: =SUM(B5:B10) -> 362499 | C11: =SUM(C5:C10) -> 362499 | D11: =SUM(D5:D10) -> 362499 | E11: =SUM(E5:E10) -> 362499 | F11: =SUM(F5:F10) -> 362499 | G11: =SUM(G5:G10) -> 362499 | H11: =SUM(H5:H10) -> 362499 | I11: =SUM(I5:I10) -> 362499 | ... M11: =SUM(M5:M10) -> 362499 | N11: =SUM(B11:M11) -> 4349988 | O11: =Revenue!E11 -> 4350000
A12: Less: Exam Fees (20%) | B12: =B11*0.05 -> 18124.95 | C12: =C11*0.05 -> 18124.95 | D12: =D11*0.05 -> 18124.95 | E12: =E11*0.05 -> 18124.95 | F12: =F11*0.05 -> 18124.95 | G12: =G11*0.05 -> 18124.95 | H12: =H11*0.05 -> 18124.95 | I12: =I11*0.05 -> 18124.95 | ... M12: =M11*0.05 -> 18124.95 | N12: =SUM(B12:M12) -> 217499.4 | O12: =Revenue!F11 -> 217500
A13: NET REVENUE | B13: =B11-B12 -> 344374.05 | C13: =C11-C12 -> 344374.05 | D13: =D11-D12 -> 344374.05 | E13: =E11-E12 -> 344374.05 | F13: =F11-F12 -> 344374.05 | G13: =G11-G12 -> 344374.05 | H13: =H11-H12 -> 344374.05 | I13: =I11-I12 -> 344374.05 | ... M13: =M11-M12 -> 344374.05 | N13: =SUM(B13:M13) -> 4132488.6 | O13: =Revenue!G11 -> 4132500
A15: MONTHLY EXPENSES
A16: Staff Salaries | B16: =(Expenses!C5+Expenses!C6)/12 -> 70000 | C16: =(Expenses!C5+Expenses!C6)/12 -> 70000 | D16: =(Expenses!C5+Expenses!C6)/12 -> 70000 | E16: =(Expenses!C5+Expenses!C6)/12 -> 70000 | F16: =(Expenses!C5+Expenses!C6)/12 -> 70000 | G16: =(Expenses!C5+Expenses!C6)/12 -> 70000 | H16: =(Expenses!C5+Expenses!C6)/12 -> 70000 | I16: =(Expenses!C5+Expenses!C6)/12 -> 70000 | J16: =(Expenses!C5+Expenses!C6)/12 -> 70000 | K16: =(Expenses!C5+Expenses!C6)/12 -> 70000 | L16: =(Expenses!C5+Expenses!C6)/12 -> 70000 | M16: =(Expenses!C5+Expenses!C6)/12 -> 70000 | N16: =SUM(B16:M16) -> 840000 | O16: =(Expenses!C5+Expenses!C6) -> 840000
A17: Advertisement | B17: =Expenses!C7/12 -> 20000 | C17: =Expenses!C7/12 -> 20000 | D17: =Expenses!C7/12 -> 20000 | E17: =Expenses!C7/12 -> 20000 | F17: =Expenses!C7/12 -> 20000 | G17: =Expenses!C7/12 -> 20000 | H17: =Expenses!C7/12 -> 20000 | I17: =Expenses!C7/12 -> 20000 | J17: =Expenses!C7/12 -> 20000 | K17: =Expenses!C7/12 -> 20000 | L17: =Expenses!C7/12 -> 20000 | M17: =Expenses!C7/12 -> 20000 | N17: =SUM(B17:M17) -> 240000 | O17: =Expenses!C7 -> 240000
A18: Technology Subscription | B18: =Expenses!C8/12 -> 30000 | C18: =Expenses!C8/12 -> 30000 | D18: =Expenses!C8/12 -> 30000 | E18: =Expenses!C8/12 -> 30000 | F18: =Expenses!C8/12 -> 30000 | G18: =Expenses!C8/12 -> 30000 | H18: =Expenses!C8/12 -> 30000 | I18: =Expenses!C8/12 -> 30000 | J18: =Expenses!C8/12 -> 30000 | K18: =Expenses!C8/12 -> 30000 | L18: =Expenses!C8/12 -> 30000 | M18: =Expenses!C8/12 -> 30000 | N18: =SUM(B18:M18) -> 360000 | O18: =Expenses!C8 -> 360000
A19: Book Printing | B19: =Expenses!C9 -> 200000 | C19: 0 | D19: 0 | E19: 0 | F19: 0 | G19: 0 | H19: 0 | I19: 0 | J19: 0 | K19: 0 | L19: 0 | M19: 0 | N19: =SUM(B19:M19) -> 200000 | O19: =Expenses!C9 -> 200000
A20: Exam Fees Payout (20%) | B20: =B12 -> 18124.95 | C20: =C12 -> 18124.95 | D20: =D12 -> 18124.95 | E20: =E12 -> 18124.95 | F20: =F12 -> 18124.95 | G20: =G12 -> 18124.95 | H20: =H12 -> 18124.95 | I20: =I12 -> 18124.95 | ... M20: =M12 -> 18124.95 | N20: =SUM(B20:M20) -> 217499.4 | O20: =Expenses!C10 -> 300000
A21: Rent | B21: =Expenses!C11/12 -> 8333.3333 | C21: =Expenses!C11/12 -> 8333.3333 | D21: =Expenses!C11/12 -> 8333.3333 | E21: =Expenses!C11/12 -> 8333.3333 | F21: =Expenses!C11/12 -> 8333.3333 | G21: =Expenses!C11/12 -> 8333.3333 | H21: =Expenses!C11/12 -> 8333.3333 | I21: =Expenses!C11/12 -> 8333.3333 | J21: =Expenses!C11/12 -> 8333.3333 | K21: =Expenses!C11/12 -> 8333.3333 | L21: =Expenses!C11/12 -> 8333.3333 | M21: =Expenses!C11/12 -> 8333.3333 | N21: =SUM(B21:M21) -> 100000 | O21: =Expenses!C11 -> 100000
A22: Misc / Transport | B22: =Expenses!C12/12 -> 170000 | C22: =Expenses!C12/12 -> 170000 | D22: =Expenses!C12/12 -> 170000 | E22: =Expenses!C12/12 -> 170000 | F22: =Expenses!C12/12 -> 170000 | G22: =Expenses!C12/12 -> 170000 | H22: =Expenses!C12/12 -> 170000 | I22: =Expenses!C12/12 -> 170000 | J22: =Expenses!C12/12 -> 170000 | K22: =Expenses!C12/12 -> 170000 | L22: =Expenses!C12/12 -> 170000 | M22: =Expenses!C12/12 -> 170000 | N22: =SUM(B22:M22) -> 2040000 | O22: =Expenses!C12 -> 2040000
A23: TOTAL OUTFLOWS | B23: =SUM(B16:B22) -> 516458.28 | C23: =SUM(C16:C22) -> 316458.28 | D23: =SUM(D16:D22) -> 316458.28 | E23: =SUM(E16:E22) -> 316458.28 | F23: =SUM(F16:F22) -> 316458.28 | G23: =SUM(G16:G22) -> 316458.28 | H23: =SUM(H16:H22) -> 316458.28 | I23: =SUM(I16:I22) -> 316458.28 | ... M23: =SUM(M16:M22) -> 316458.28 | N23: =SUM(B23:M23) -> 3997499.4 | O23: =Expenses!C13 -> 0
A25: NET MONTHLY CASH FLOW | B25: =B13-B23 -> -172084.23 | C25: =C13-C23 -> 27915.767 | D25: =D13-D23 -> 27915.767 | E25: =E13-E23 -> 27915.767 | F25: =F13-F23 -> 27915.767 | G25: =G13-G23 -> 27915.767 | H25: =H13-H23 -> 27915.767 | I25: =I13-I23 -> 27915.767 | ... M25: =M13-M23 -> 27915.767 | N25: =SUM(B25:M25) -> 134989.2
A26: CUMULATIVE CASH FLOW | B26: =B25 -> -172084.23 | C26: =B26+C25 -> -144168.47 | D26: =C26+D25 -> -116252.7 | E26: =D26+E25 -> -88336.933 | F26: =E26+F25 -> -60421.167 | G26: =F26+G25 -> -32505.4 | H26: =G26+H25 -> -4589.6333 | I26: =H26+I25 -> 23326.133 | J26: =I26+J25 -> 51241.9 | ... M26: =L26+M25 -> 134989.2 | N26: =M26 -> 134989.2
A29: BATCH SCHEDULE REFERENCE
A30: Course | B30: Duration | C30: Admissions | D30: Batches/Year | E30: Batch Start Months
A31: Spoken English | B31: 3 Months | C31: 100 | D31: 4 | E31: Apr-26, Jul-26, Oct-26, Jan-27 (25 students per batch)
A32: Phonics & Early Literacy | B32: 3 Months | C32: 100 | D32: 4 | E32: Apr-26, Jul-26, Oct-26, Jan-27 (25 students per batch)
A33: Child Psychology | B33: 3 Months | C33: 50 | D33: 4 | E33: Apr-26, Jul-26, Oct-26, Jan-27 (12-13 per batch)
A34: Montessori & Primary Diploma | B34: 6 Months | C34: 100 | D34: 2 | E34: Apr-26 & Oct-26 (50 students per batch)
A35: Special Needs Education | B35: 6 Months | C35: 50 | D35: 2 | E35: Apr-26 & Oct-26 (25 students per batch)
A36: Digital Marketing | B36: 3 Months | C36: 20 | D36: 4 | E36: Apr-26, Jul-26, Oct-26, Jan-27 (5 students per batch)

Sheet Break-Even Analysis
A1: ANSA MONTESSORI — BREAK-EVEN ANALYSIS
A3: FIXED COSTS, VARIABLE COSTS & BREAK-EVEN POINT
A4: Description | B4: Amount (₹) | C4: Basis
A5: FIXED COSTS (Annual)
A6: Teacher & Staff Salaries | B6: =Expenses!C5+Expenses!C6 -> 840000 | C6: Fixed monthly regardless of admissions
A7: Advertisement | B7: =Expenses!C7 -> 240000 | C7: Fixed monthly budget
A8: Technology Subscription | B8: =Expenses!C8 -> 360000 | C8: Fixed SaaS/LMS cost
A9: Book Printing | B9: =Expenses!C9 -> 200000 | C9: One-time annual
A10: Rent | B10: =Expenses!C11 -> 100000 | C10: Fixed annual rent
A11: Transport & Miscellaneous | B11: =Expenses!C12 -> 2040000 | C11: Fixed estimate
A12: Total Fixed Costs | B12: =SUM(B6:B11) -> 3780000
A14: VARIABLE COSTS
A15: Exam Fees (20% of Gross Revenue) | B15: =Expenses!C10 -> 300000 | C15: Variable — scales with revenue
A17: BREAK-EVEN CALCULATION
A18: Total Admissions (Current) | B18: =Revenue!D11 -> 420 | C18: Sum of all enrolled students
A19: Avg Revenue per Student (₹) | B19: =IF(Revenue!D11>0,Revenue!E11/Revenue!D11,0) -> 10357.143 | C19: Gross Rev ÷ Total Admissions
A20: Avg Variable Cost per Student (₹) | B20: =IF(Revenue!D11>0,Expenses!C10/Revenue!D11,0) -> 714.28571 | C20: Exam Fee ÷ Total Admissions
A21: Contribution per Student (₹) | B21: =B19-B20 -> 9642.8571 | C21: Avg Rev minus Avg Variable Cost
A22: Break-Even Admissions (nos.) | B22: =IF(B21>0,CEILING(B12/B21,1),"N/A") -> 392 | C22: Fixed Costs ÷ Contribution per Student
A23: Current Admissions vs Break-Even | B23: =Revenue!D11-B22 -> 28 | C23: Surplus admissions above break-even
A24: Break-Even Revenue (₹) | B24: =B22*B19 -> 4060000 | C24: Break-Even Admissions × Avg Rev/Student
A25: Safety Margin (%) | B25: =IF(Revenue!E11>0,(Revenue!E11-B24)/Revenue!E11,0) -> 0.066666667 | C25: (Actual Rev - BE Rev) ÷ Actual Rev

Sheet 3-Year Projection
A1: ANSA MONTESSORI — 3-YEAR FINANCIAL PROJECTION
A3: GROWTH ASSUMPTIONS & PROJECTED P&L (FY1 = Current Year Actuals)
A5: GROWTH ASSUMPTIONS (Editable — Blue Cells)
A6: Assumption | B6: FY1 (Base) | C6: FY2 Growth % | D6: FY3 Growth % | E6: Notes
A7: Admission Growth Rate | B7: - | C7: 0.2 | D7: 0.2 | E7: 20% YoY growth in student admissions
A8: Fee Revision Rate | B8: - | C8: 0.05 | D8: 0.05 | E8: 5% annual fee increase
A9: Salary Increment Rate | B9: - | C9: 0.1 | D9: 0.1 | E9: 10% annual staff salary increase
A10: Fixed Cost Growth Rate | B10: - | C10: 0.05 | D10: 0.05 | E10: 5% increase in other fixed costs
A12: PROJECTED P&L
A13: Metric | B13: FY1 (Current) | C13: FY2 (Projected) | D13: FY3 (Projected) | E13: 3-Year Total
A14: Total Admissions | B14: =Revenue!D13 -> 0 | C14: =ROUND(B14*(1+C7),0) -> 0 | D14: =ROUND(C14*(1+D7),0) -> 0 | E14: =SUM(B14:D14) -> 0
A15: Avg Fee per Student (₹) | B15: =IF(Revenue!D13>0,Revenue!E13/Revenue!D13,0) -> 0 | C15: =B15*(1+C8) -> 0 | D15: =C15*(1+D8) -> 0 | E15: -
A16: Gross Revenue (₹) | B16: =Revenue!E13 -> 0 | C16: =C14*C15 -> 0 | D16: =D14*D15 -> 0 | E16: =SUM(B16:D16) -> 0
A17: Exam Fees 20% (₹) | B17: =Revenue!F13 -> 0 | C17: =C16*0.05 -> 0 | D17: =D16*0.05 -> 0 | E17: =SUM(B17:D17) -> 0
A18: Net Revenue (₹) | B18: =Revenue!G13 -> 0 | C18: =C16-C17 -> 0 | D18: =D16-D17 -> 0 | E18: =SUM(B18:D18) -> 0
A19: Staff Salaries (₹) | B19: =Expenses!C5+Expenses!C6 -> 840000 | C19: =B19*(1+C9) -> 924000 | D19: =C19*(1+D9) -> 1016400 | E19: =SUM(B19:D19) -> 2780400
A20: Other Fixed Costs (₹) | B20: =Expenses!C7+Expenses!C8+Expenses!C9+Expenses!C11+Expenses!C12 -> 2940000 | C20: =B20*(1+C10) -> 3087000 | D20: =C20*(1+D10) -> 3241350 | E20: =SUM(B20:D20) -> 9268350
A21: Total Expenses (₹) | B21: =Expenses!C12 -> 2040000 | C21: =C17+C19+C20 -> 4011000 | D21: =D17+D19+D20 -> 4257750 | E21: =SUM(B21:D21) -> 10308750
A22: NET PROFIT (₹) | B22: ='P&L Summary'!B14 -> 0 | C22: =C18-C21 -> -4011000 | D22: =D18-D21 -> -4257750 | E22: =SUM(B22:D22) -> -8268750
A23: Profit Margin (%) | B23: ='P&L Summary'!B15 -> 0 | C23: =IF(C18>0,C22/C18,0) -> 0 | D23: =IF(D18>0,D22/D18,0) -> 0 | E23: -

Sheet Franchise Model
A1: ANSA MONTESSORI — FRANCHISE REVENUE MODEL
A3: PER-PARTNER ECONOMICS & TOTAL FRANCHISE NETWORK REVENUE
A5: FRANCHISE ASSUMPTIONS (Editable)
A6: Parameter | B6: Value | C6: Unit | D6: Notes
A7: Franchise Fee (One-Time) | B7: 50000 | C7: ₹ per partner | D7: Initial onboarding fee
A8: Revenue Share to ANSA (%) | B8: 0.15 | C8: % of partner gross rev | D8: ANSA earns 15% of partner revenue
A9: Avg Admissions per Partner / yr | B9: 60 | C9: Students | D9: Conservative estimate
A10: Avg Course Fee per Student | B10: 10000 | C10: ₹ | D10: Blended average across courses
A11: No. of Active Partners | B11: 50 | C11: Partners | D11: Current network size
A12: New Partners Added (Annual) | B12: 10 | C12: Partners | D12: Growth target
A14: FRANCHISE NETWORK REVENUE TO ANSA
A15: Revenue Stream | B15: Calculation | C15: Annual Amount (₹) | D15: Notes
A16: One-Time Franchise Fees (New) | B16: =B12*B7 -> 500000 | C16: =B12*B7 -> 500000 | D16: New partners × franchise fee
A17: Revenue Share from Network | B17: =B11*B9*B10*B8 -> 4500000 | C17: =B11*B9*B10*B8 -> 4500000 | D17: Partners × admissions × avg fee × share %
A18: Total Franchise Income | B18: =C16+C17 -> 5000000 | C18: =C16+C17 -> 5000000 | D18: Combined franchise revenue to ANSA
A20: PARTNER P&L (Per Franchise Center)
A21: Item | B21: Annual Amount (₹) | C21: Notes
A22: Gross Revenue (Partner) | B22: =B9*B10 -> 600000 | C22: Admissions × avg fee
A23: Revenue Shared to ANSA | B23: =B22*B8 -> 90000 | C23: 15% royalty to ANSA
A24: Net Revenue (Partner Keeps) | B24: =B22-B23 -> 510000 | C24: After paying ANSA share
A25: Est. Operating Costs | B25: =B22*0.5 -> 300000 | C25: ~50% cost ratio for ops/staff/rent
A26: Partner Net Profit | B26: =B24-B25 -> 210000 | C26: Net after ops and ANSA share
A27: Partner ROI (on ₹2L invest) | B27: =IF(200000>0,B26/200000,0) -> 1.05 | C27: Return on ₹2 lakh investment

Sheet Fee Collection Tracker
A1: ANSA MONTESSORI — FEE COLLECTION & EMI TRACKER
A3: EXPECTED vs COLLECTED FEES PER COURSE (Enter actual collections in yellow cells)
A4: Course | B4: Admissions | C4: Fee (₹) | D4: Expected Total (₹) | E4: Collected (₹) | F4: Pending (₹) | G4: Collection % | H4: EMI Students
A5: Spoken English | B5: =Revenue!D5 -> 100 | C5: =Revenue!B5 -> 4000 | D5: =B5*C5 -> 400000 | E5: 0 | F5: =D5-E5 -> 400000 | G5: =IF(D5>0,E5/D5,0) -> 0 | H5: 0
A6: Phonics | B6: =Revenue!D6 -> 100 | C6: =Revenue!B6 -> 4000 | D6: =B6*C6 -> 400000 | E6: 0 | F6: =D6-E6 -> 400000 | G6: =IF(D6>0,E6/D6,0) -> 0 | H6: 0
A7: Child Psychology | B7: =Revenue!D7 -> 50 | C7: =Revenue!B7 -> 6000 | D7: =B7*C7 -> 300000 | E7: 0 | F7: =D7-E7 -> 300000 | G7: =IF(D7>0,E7/D7,0) -> 0 | H7: 0
A8: Montessori & Primary Diploma | B8: =Revenue!D8 -> 100 | C8: =Revenue!B8 -> 25000 | D8: =B8*C8 -> 2500000 | E8: 0 | F8: =D8-E8 -> 2500000 | G8: =IF(D8>0,E8/D8,0) -> 0 | H8: 0
A9: Special Needs Education | B9: =Revenue!D9 -> 50 | C9: =Revenue!B9 -> 9000 | D9: =B9*C9 -> 450000 | E9: 0 | F9: =D9-E9 -> 450000 | G9: =IF(D9>0,E9/D9,0) -> 0 | H9: 0
A10: Digital Marketing | B10: =Revenue!D10 -> 20 | C10: =Revenue!B10 -> 15000 | D10: =B10*C10 -> 300000 | E10: 0 | F10: =D10-E10 -> 300000 | G10: =IF(D10>0,E10/D10,0) -> 0 | H10: 0
A11: TOTAL | B11: =Revenue!D11 -> 420 | D11: =SUM(D5:D10) -> 4350000 | E11: =SUM(E5:E10) -> 0 | F11: =SUM(F5:F10) -> 4350000 | G11: =IF(D11>0,E11/D11,0) -> 0 | H11: =SUM(H5:H10) -> 0
A13: 📌 Yellow cells = Enter actual collected amounts and EMI student counts.

Sheet Enrollment Funnel
A1: ANSA MONTESSORI — STUDENT ENROLLMENT FUNNEL
A2: Track leads → enquiries → applications → enrolments → completions per course
A4: FUNNEL STAGE OVERVIEW (Enter actual numbers in yellow cells)
A5: Funnel Stage | B5: Count | C5: % of Leads | D5: Drop-Off Count | E5: Drop-Off % | F5: Benchmark | G5: Status
A6: 🔵 Total Leads / Inquiries Received | B6: 1000 | C6: =IF($B$6>0,B6/$B$6,0) -> 1 | D6: — | E6: — | F6: Industry target: 1,000+/yr | G6: =IF(B6>=1000,"✅ On Track","⚠️ Below Target") -> ✅ On Track
A7: 🟡 Enquiry Calls Made (Tele-Caller) | B7: 700 | C7: =IF($B$6>0,B7/$B$6,0) -> 0.7 | D7: =B6-B7 -> 300 | E7: =IF(B6>0,(B6-B7)/B6,0) -> 0.3 | F7: Target: 70%+ of leads called | G7: =IF(C7>=0.7,"✅ On Track","⚠️ Below Target") -> ✅ On Track
A8: 🟠 Counselling Sessions Completed | B8: 400 | C8: =IF($B$6>0,B8/$B$6,0) -> 0.4 | D8: =B7-B8 -> 300 | E8: =IF(B7>0,(B7-B8)/B7,0) -> 0.42857143 | F8: Target: 57%+ of calls | G8: =IF(C8>=0.57,"✅ On Track","⚠️ Below Target") -> ⚠️ Below Target
A9: 🟢 Applications Submitted | B9: 200 | C9: =IF($B$6>0,B9/$B$6,0) -> 0.2 | D9: =B8-B9 -> 200 | E9: =IF(B8>0,(B8-B9)/B8,0) -> 0.5 | F9: Target: 50%+ of counselled | G9: =IF(C9>=0.5,"✅ On Track","⚠️ Below Target") -> ⚠️ Below Target
A10: ✅ Confirmed Admissions (Paid) | B10: =Revenue!D13 -> 0 | C10: =IF($B$6>0,B10/$B$6,0) -> 0 | D10: =B9-B10 -> 200 | E10: =IF(B9>0,(B9-B10)/B9,0) -> 1 | F10: Target: 75%+ of applications | G10: =IF(C10>=0.75,"✅ On Track","⚠️ Below Target") -> ⚠️ Below Target
A11: 📚 Active Students (Currently Learning) | B11: 380 | C11: =IF($B$6>0,B11/$B$6,0) -> 0.38 | D11: =B10-B11 -> -380 | E11: =IF(B10>0,(B10-B11)/B10,0) -> 0 | F11: Should match Admissions - Dropouts | G11: =IF(B11>=B10,"✅ On Track","⚠️ Check Dropouts") -> ✅ On Track
A12: 🎓 Course Completions (Certified) | B12: 350 | C12: =IF($B$6>0,B12/$B$6,0) -> 0.35 | D12: =B11-B12 -> 30 | E12: =IF(B11>0,(B11-B12)/B11,0) -> 0.078947368 | F12: Target: 90%+ completion rate | G12: =IF(C12>=0.9,"✅ On Track","⚠️ Below Target") -> ⚠️ Below Target
A13: 💼 Placed / Employed Post-Course | B13: 343 | C13: =IF($B$6>0,B13/$B$6,0) -> 0.343 | D13: =B12-B13 -> 7 | E13: =IF(B12>0,(B12-B13)/B12,0) -> 0.02 | F13: Target: 98% placement rate | G13: =IF(C13>=0.98,"✅ On Track","⚠️ Below Target") -> ⚠️ Below Target
A15: COURSE-WISE ENROLLMENT BREAKDOWN
A16: Course | B16: Target Admissions | C16: Actual Admissions | D16: Active Students | E16: Completions | F16: Dropout Count | G16: Completion Rate %
A17: Spoken English | B17: 100 | C17: =Revenue!D5 -> 100 | D17: 95 | E17: 90 | F17: =C17-D17 -> 5 | G17: =IF(C17>0,E17/C17,0) -> 0.9
A18: Phonics & Early Literacy | B18: 100 | C18: =Revenue!D6 -> 100 | D18: 96 | E18: 92 | F18: =C18-D18 -> 4 | G18: =IF(C18>0,E18/C18,0) -> 0.92
A19: Child Psychology | B19: 50 | C19: =Revenue!D7 -> 50 | D19: 48 | E19: 46 | F19: =C19-D19 -> 2 | G19: =IF(C19>0,E19/C19,0) -> 0.92
A20: Montessori & Primary Diploma | B20: 100 | C20: =Revenue!D8 -> 100 | D20: 98 | E20: 95 | F20: =C20-D20 -> 2 | G20: =IF(C20>0,E20/C20,0) -> 0.95
A21: Special Needs Education | B21: 50 | C21: =Revenue!D9 -> 50 | D21: 47 | E21: 45 | F21: =C21-D21 -> 3 | G21: =IF(C21>0,E21/C21,0) -> 0.9
A22: Digital Marketing | B22: 20 | C22: =Revenue!D10 -> 20 | D22: 18 | E22: 17 | F22: =C22-D22 -> 2 | G22: =IF(C22>0,E22/C22,0) -> 0.85
A23: TOTAL | B23: =SUM(B17:B22) -> 420 | C23: =Revenue!D11 -> 420 | D23: =SUM(D17:D22) -> 402 | E23: =SUM(E17:E22) -> 385 | F23: =SUM(F17:F22) -> 18 | G23: =IF(C23>0,E23/C23,0) -> 0.91666667
A27: KEY CONVERSION METRICS
A28: Metric | B28: Value | C28: Formula Basis
A29: Lead-to-Enquiry Conversion | B29: =IF(B6>0,B7/B6,0) -> 0.7 | C29: Enquiry Calls ÷ Total Leads
A30: Enquiry-to-Counselling Rate | B30: =IF(B7>0,B8/B7,0) -> 0.57142857 | C30: Counselling Sessions ÷ Calls
A31: Counselling-to-Application Rate | B31: =IF(B8>0,B9/B8,0) -> 0.5 | C31: Applications ÷ Counselling
A32: Application-to-Admission Rate | B32: =IF(B9>0,B10/B9,0) -> 0 | C32: Admissions ÷ Applications
A33: Overall Lead-to-Admission Rate | B33: =IF(B6>0,B10/B6,0) -> 0 | C33: Admissions ÷ Total Leads
A34: Overall Completion Rate | B34: =IF(B10>0,B12/B10,0) -> 0 | C34: Completions ÷ Admissions
A35: Post-Course Placement Rate | B35: =IF(B12>0,B13/B12,0) -> 0.98 | C35: Placed ÷ Completions
A36: Cost per Enrolled Student (₹) | B36: =IF(Revenue!D13>0,Expenses!C7/Revenue!D13,0) -> 0 | C36: Ad Spend ÷ Total Admissions
A37: Revenue per Lead (₹) | B37: =IF(B6>0,Revenue!E13/B6,0) -> 0 | C37: Gross Revenue ÷ Total Leads
A39: 📌 Yellow cells = Enter actual data. Blue cells = Editable targets/inputs. Green cells = Linked from Revenue sheet.
